yamliny/__init__.py
yamliny/__version.py
yamliny/_yamliny.py
yamliny/py.typed
yamliny-0.0.2.dist-info/LICENSE
yamliny-0.0.2.dist-info/METADATA
yamliny-0.0.2.dist-info/WHEEL
yamliny-0.0.2.dist-info/top_level.txt
yamliny-0.0.2.dist-info/RECORD
