Metadata-Version: 2.1
Name: yamliny
Version: 0.0.2
Summary: Parser for a tiny subset of YAML; YAML lite
Home-page: https://github.com/slarse/yamliny
Author: Simon Larsén
Author-email: slarse@slar.se
License: MIT
Download-URL: https://github.com/slarse/yamliny/archive/v0.0.2.tar.gz
Platform: UNKNOWN
Classifier: Development Status :: 3 - Alpha
Classifier: Intended Audience :: Education
Classifier: Programming Language :: Python :: 3.6
Classifier: Programming Language :: Python :: 3.7
Classifier: Programming Language :: Python :: 3.8
Classifier: Programming Language :: Python :: 3.9
Classifier: Programming Language :: Python :: 3.10
Classifier: Programming Language :: Python :: Implementation :: CPython
Classifier: License :: OSI Approved :: MIT License
Classifier: Operating System :: POSIX
Classifier: Operating System :: Microsoft :: Windows
License-File: LICENSE
Provides-Extra: test
Requires-Dist: pytest (>=4.0.0) ; extra == 'test'
Requires-Dist: pyyaml ; extra == 'test'
